my_package/__init__.py
my_package/greeting.py
tbotssinr-0.1.0.dist-info/METADATA
tbotssinr-0.1.0.dist-info/WHEEL
tbotssinr-0.1.0.dist-info/top_level.txt
tbotssinr-0.1.0.dist-info/RECORD
