Metadata-Version: 2.4
Name: TBOTSSINR
Version: 0.1.0
Summary: A test package for learning PyPI uploads
Author-email: ashlee0410 <lhuntion@naver.com>
License: MIT
Project-URL: Homepage, https://github.com/ashlee-arch/my-first-pypi-test
Classifier: Programming Language :: Python :: 3
Classifier: License :: OSI Approved :: MIT License
Classifier: Operating System :: OS Independent
Requires-Python: >=3.7
